rockstarpy/__init__.py
rockstarpy/__main__.py
rockstarpy/command_line.py
rockstarpy/transpile.py
rockstar_py-2.1.0.dist-info/LICENSE
rockstar_py-2.1.0.dist-info/METADATA
rockstar_py-2.1.0.dist-info/WHEEL
rockstar_py-2.1.0.dist-info/entry_points.txt
rockstar_py-2.1.0.dist-info/top_level.txt
rockstar_py-2.1.0.dist-info/RECORD
