Metadata-Version: 2.1
Name: rockstar-py
Version: 2.1.0
Summary: Python transpiler for the esoteric language Rockstar
Home-page: https://github.com/yyyyyyyan/rockstar-py
Author: yyyyyyyan
Author-email: contact@yyyyyyyan.tech
License: MIT
Download-URL: https://github.com/yyyyyyyan/rockstar-py/archive/2.1.0.zip
Keywords: esoteric rockstar transpiler
Platform: UNKNOWN
Classifier: Development Status :: 5 - Production/Stable
Classifier: Environment :: Console
Classifier: Intended Audience :: Developers
Classifier: License :: OSI Approved :: MIT License
Classifier: Natural Language :: English
Classifier: Operating System :: OS Independent
Classifier: Programming Language :: Python :: 3
Classifier: Programming Language :: Python :: 3 :: Only
Classifier: Programming Language :: Python :: 3.6
Classifier: Programming Language :: Python :: 3.7
Classifier: Programming Language :: Python :: 3.8
Classifier: Programming Language :: Python :: 3.9
Classifier: Topic :: Software Development :: Compilers
Classifier: Topic :: Software Development :: Interpreters
Requires-Python: >= 3.6
